README.txt
setup.py
prettypandas/__init__.py
prettypandas/formatters.py
prettypandas/summarizer.py
prettypandas.egg-info/PKG-INFO
prettypandas.egg-info/SOURCES.txt
prettypandas.egg-info/dependency_links.txt
prettypandas.egg-info/requires.txt
prettypandas.egg-info/top_level.txt
test/test_pretty_pandas.py