Metadata-Version: 1.1
Name: prettypandas
Version: 0.0.4
Summary: Pandas Styler for Report Quality Tables.
Home-page: https://github.com/HHammond/PrettyPandas
Author: Henry Hammond
Author-email: henryhhammond92@gmail.com
License: MIT
Keywords: pandas pretty display tables reporting
Platform: UNKNOWN
Classifier: Development Status :: 3 - Alpha
Classifier: Intended Audience :: Science/Research
Classifier: Topic :: Scientific/Engineering
Classifier: License :: OSI Approved :: MIT License
Classifier: Programming Language :: Python :: 2
Classifier: Programming Language :: Python :: 2.7
Classifier: Programming Language :: Python :: 3
Classifier: Programming Language :: Python :: 3.2
Classifier: Programming Language :: Python :: 3.3
Classifier: Programming Language :: Python :: 3.4
Classifier: Programming Language :: Python :: 3.5
